tcd/__init__.py
tcd/__main__.py
tcd/example.settings.json
tcd/settings.py
tcd/subtitles.py
tcd/twitch.py
tdh_tcd-2.5.4.dist-info/LICENSE
tdh_tcd-2.5.4.dist-info/METADATA
tdh_tcd-2.5.4.dist-info/WHEEL
tdh_tcd-2.5.4.dist-info/entry_points.txt
tdh_tcd-2.5.4.dist-info/top_level.txt
tdh_tcd-2.5.4.dist-info/RECORD
