Metadata-Version: 2.1
Name: tdh-tcd
Version: 2.5.4
Summary: Twitch Chat Downloader
Home-page: https://github.com/TheDrHax/Twitch-Chat-Downloader
Author: Dmitry Karikh
Author-email: the.dr.hax@gmail.com
Classifier: Environment :: Console
Classifier: Programming Language :: Python :: 3.6
Classifier: Intended Audience :: End Users/Desktop
Classifier: License :: OSI Approved :: MIT License
Classifier: Operating System :: OS Independent
Classifier: Topic :: Utilities
License-File: LICENSE
Requires-Dist: requests
Requires-Dist: progressbar2
Requires-Dist: iso8601
